{
  "hash": "07cd665e",
  "configHash": "c8e048d2",
  "lockfileHash": "241d8055",
  "browserHash": "e43b9178",
  "optimized": {
    "react": {
      "src": "../../node_modules/react/index.js",
      "file": "react.js",
      "fileHash": "1289c947",
      "needsInterop": true
    },
    "react-dom/client": {
      "src": "../../node_modules/react-dom/client.js",
      "file": "react-dom_client.js",
      "fileHash": "5ff577fa",
      "needsInterop": true
    }
  },
  "chunks": {
    "chunk-SS3IWWB5": {
      "file": "chunk-SS3IWWB5.js"
    }
  }
}